queryverse-0.1.4.dist-info/METADATA
queryverse-0.1.4.dist-info/WHEEL
queryverse/__init__.py
queryverse/llm/__init__.py
queryverse/llm/llm.py
queryverse/llm/open_ai.py
queryverse/prompter/__init__.py
queryverse/prompter/prompter.py
queryverse-0.1.4.dist-info/RECORD
